setup.py
resty/__init__.py
resty/documents.py
resty/types.py
resty.egg-info/PKG-INFO
resty.egg-info/SOURCES.txt
resty.egg-info/dependency_links.txt
resty.egg-info/requires.txt
resty.egg-info/top_level.txt
resty/tests/__init__.py
resty/tests/mocks.py
resty/tests/test_client.py
resty/tests/test_document_types.py
resty/tests/test_documents.py
resty/tests/test_e2e.py
resty/tests/test_pickle.py