Metadata-Version: 1.0
Name: resty
Version: 0.1.1
Summary: PBS API consumer library
Home-page: https://github.com/pbs/resty
Author: TPG CORE Services Team
Author-email: tpg-pbs-coreservices@threepillarglobal.com
License: UNKNOWN
Platform: UNKNOWN
